{"tuv":{"tuvCannotStoreDoc":"Error occured while storing the pdf document from the TUV Report.","tuvAddressError":"The TUV service address is not configured.","tuvCannotStoreImg":"Error occured while storing the images from the TUV Report.","tuvNoReportAvailableError":"There is no TUV expertise report available.","document":{"description":""},"tuvCannotStoreExpertiseData":"Error occured while storing the expertise data from the TUV Report.","tuvDbError":"Error while retrieving/saving TUV data in database.","tuvError":"Error when accessing the TUV service.","tuvAuthError":"User and/or password for TUV service are not configured."}}